flask_fcmadmin/__init__.py
flask_fcmadmin/flask_fcm_center.py
flask_fcmadmin/cloud_messaging/__init__.py
flask_fcmadmin/cloud_messaging/component_builders/__init__.py
flask_fcmadmin/cloud_messaging/component_builders/android_builder.py
flask_fcmadmin/cloud_messaging/component_builders/android_fcm_options_builder.py
flask_fcmadmin/cloud_messaging/component_builders/android_notification_builder.py
flask_fcmadmin/cloud_messaging/component_builders/apns_aps_alert_builder.py
flask_fcmadmin/cloud_messaging/component_builders/apns_aps_builder.py
flask_fcmadmin/cloud_messaging/component_builders/apns_aps_critical_sound_builder.py
flask_fcmadmin/cloud_messaging/component_builders/apns_builder.py
flask_fcmadmin/cloud_messaging/component_builders/apns_fcm_options_builder.py
flask_fcmadmin/cloud_messaging/component_builders/apns_payload_builder.py
flask_fcmadmin/cloud_messaging/component_builders/fcm_options_builder.py
flask_fcmadmin/cloud_messaging/component_builders/light_setting_builder.py
flask_fcmadmin/cloud_messaging/component_builders/notification_builder.py
flask_fcmadmin/cloud_messaging/message/__init__.py
flask_fcmadmin/cloud_messaging/message/message.py
flask_fcmadmin/cloud_messaging/utils/__init__.py
flask_fcmadmin/cloud_messaging/utils/priority_type.py
flask_fcmadmin/cloud_messaging/utils/visibility_type.py
flask_FCMAdmin-0.0.9.dist-info/LICENSE
flask_FCMAdmin-0.0.9.dist-info/METADATA
flask_FCMAdmin-0.0.9.dist-info/WHEEL
flask_FCMAdmin-0.0.9.dist-info/top_level.txt
flask_FCMAdmin-0.0.9.dist-info/RECORD
